lpath/__init__.py
lpath/_logger.py
lpath/_version.py
lpath/argparser.py
lpath/discretize.py
lpath/extloader.py
lpath/extract.py
lpath/io.py
lpath/lpath.py
lpath/match.py
lpath/plot.py
lpath/py.typed
lpath/data/styles/default.mplstyle
lpath/tests/__init__.py
lpath/tests/conftest.py
lpath/tests/test_argparser.py
lpath/tests/test_discretize.py
lpath/tests/test_extract.py
lpath/tests/test_lpath.py
lpath/tests/test_match.py
lpath/tests/test_plot.py
lpath_md-1.0.7.dist-info/LICENSE
lpath_md-1.0.7.dist-info/METADATA
lpath_md-1.0.7.dist-info/WHEEL
lpath_md-1.0.7.dist-info/entry_points.txt
lpath_md-1.0.7.dist-info/top_level.txt
lpath_md-1.0.7.dist-info/RECORD
