Metadata-Version: 2.2
Name: lpath-md
Version: 1.0.7
Summary: A user-friendly, Python tool for clustering pathways from molecular dynamics simulations.
Author-email: Anthony Bogetti <atb43@pitt.edu>, Jeremy Leung <jml230@pitt.edu>, Lillian Chong <lchong@pitt.edu>
Maintainer-email: Jeremy Leung <jml230@pitt.edu>
License: MIT
Project-URL: Source, https://github.com/chonglab-pitt/lpath/
Project-URL: Documentation, https://lpath.readthedocs.io/
Classifier: License :: OSI Approved :: MIT License
Classifier: Programming Language :: Python :: 3
Requires-Python: >=3.8
License-File: LICENSE
Requires-Dist: scikit-learn
Requires-Dist: scipy
Requires-Dist: numpy
Requires-Dist: pylcs
Requires-Dist: ray
Requires-Dist: tqdm
Requires-Dist: networkx
Requires-Dist: matplotlib>=3.6.0
Requires-Dist: timedinput
Requires-Dist: importlib-resources; python_version < "3.10"
Provides-Extra: test
Requires-Dist: pytest>=6.1.2; extra == "test"
Requires-Dist: pytest-runner; extra == "test"
Provides-Extra: westpa
Requires-Dist: westpa>=2022.03; extra == "westpa"
Provides-Extra: tui
Requires-Dist: argparse-tui>0.2.5; extra == "tui"
Provides-Extra: dev
Requires-Dist: lpath[test,tui,westpa]; extra == "dev"
